py_design-2.1.dist-info/METADATA
py_design-2.1.dist-info/WHEEL
py_design-2.1.dist-info/LICENSE.txt
_designfortran.cpython-312-darwin.so
design/__init__.py
py_design-2.1.dist-info/RECORD
