Metadata-Version: 2.1
Name: py-design
Version: 2.1
Summary: Design points for random experiments
Keywords: design,random experiment,latin hypercube,sparse grid,computer experiments
Author-Email: Ilias Bilionis <ibilion@purdue.edu>
License: GNU LESSER GENERAL PUBLIC LICENSE
Classifier: Programming Language :: Python :: 3
Classifier: Programming Language :: Fortran
Classifier: License :: OSI Approved :: MIT License
Classifier: Topic :: Scientific/Engineering
Project-URL: Homepage, https://github.com/ebilionis/py-design
Requires-Dist: numpy
